pypvwatts/__init__.py
pypvwatts/__version__.py
pypvwatts/pvwattserror.py
pypvwatts/pvwattsresult.py
pypvwatts/pypvwatts.py
pypvwatts/test.py
pypvwatts-3.0.4.dist-info/LICENSE
pypvwatts-3.0.4.dist-info/METADATA
pypvwatts-3.0.4.dist-info/WHEEL
pypvwatts-3.0.4.dist-info/top_level.txt
pypvwatts-3.0.4.dist-info/RECORD
