Metadata-Version: 2.1
Name: pypvwatts
Version: 3.0.4
Summary: Python wrapper for NREL PVWatts's API.
Home-page: https://github.com/mpaolino/pypvwatts
Author: Miguel Paolino
Author-email: mpaolino@gmail.com
License: MIT
Download-URL: https://github.com/mpaolino/pypvwatts/archive/master.zip
Keywords: nrel pvwatts pypvwatts
Platform: UNKNOWN
Classifier: Development Status :: 5 - Production/Stable
Classifier: Intended Audience :: Developers
Classifier: Natural Language :: English
Classifier: Operating System :: OS Independent
Classifier: Programming Language :: Python :: 2
Classifier: License :: OSI Approved :: MIT License
Classifier: Topic :: Internet
Classifier: Topic :: Internet :: WWW/HTTP
Requires: requests
Provides: pypvwatts
Requires-Python: >=2.7
Requires-Dist: requests (>=2.1.0)
